pypingdom/__init__.py
pypingdom/api.py
pypingdom/check.py
pypingdom/client.py
pypingdom/gui.py
pypingdom/maintenance.py
pypingdom-0.2.2.dist-info/AUTHORS
pypingdom-0.2.2.dist-info/LICENSE
pypingdom-0.2.2.dist-info/METADATA
pypingdom-0.2.2.dist-info/WHEEL
pypingdom-0.2.2.dist-info/top_level.txt
pypingdom-0.2.2.dist-info/zip-safe
pypingdom-0.2.2.dist-info/RECORD
