Metadata-Version: 2.1
Name: pypingdom
Version: 0.2.2
Summary: Client for Pingdom Services
Home-page: https://github.com/sekipaolo/pypingdom
Author: Paolo Sechi
Author-email: sekipaolo@gmail.com
License: Apache v2.0
Platform: Posix; MacOS X; Windows
Classifier: Development Status :: 3 - Alpha
Classifier: Intended Audience :: Developers
Classifier: Intended Audience :: System Administrators
Classifier: License :: OSI Approved :: Apache Software License
Classifier: Operating System :: OS Independent
Classifier: Topic :: System :: Monitoring
Classifier: Programming Language :: Python
Classifier: Programming Language :: Python :: 2.7
Classifier: Programming Language :: Python :: 3.6
Requires-Dist: requests (>=0.10.8)
Requires-Dist: six (>=1.10.0)
